c581/__init__.py
c581-0.0.0.dist-info/LICENSE
c581-0.0.0.dist-info/METADATA
c581-0.0.0.dist-info/WHEEL
c581-0.0.0.dist-info/RECORD
