Metadata-Version: 2.1
Name: c581
Version: 0.0.0
Summary: DO NOT USE THIS PACKAGE.
License: UNLICENSED
Author: Coefficient Systems Ltd
Author-email: contact@coefficient.ai
Requires-Python: >=3.12.2,<4.0.0
Classifier: License :: Other/Proprietary License
Classifier: Private :: Do Not Upload
Classifier: Programming Language :: Python :: 3
Requires-Dist: typer (>=0.12.3,<0.13.0)
